.gitignore
.gitmodules
README.md
setup.py
bin/fabsible-clean
bin/fabsible-init
bin/fabsible-play
lib/fabsible/__init__.py
lib/fabsible/my_module.py
lib/fabsible.egg-info/PKG-INFO
lib/fabsible.egg-info/SOURCES.txt
lib/fabsible.egg-info/dependency_links.txt
lib/fabsible.egg-info/requires.txt
lib/fabsible.egg-info/top_level.txt
lib/fabsible/data/cfg/fabsible.cfg
lib/fabsible/data/playbooks/site.yml
lib/fabsible/data/roles/exphost.default_filler/.gitignore
lib/fabsible/data/roles/exphost.default_filler/filter_plugins/retemplate.py
lib/fabsible/data/roles/exphost.default_filler/tasks/app_loop.yml
lib/fabsible/data/roles/exphost.default_filler/tasks/app_loop_type.yml
lib/fabsible/data/roles/exphost.default_filler/tasks/main.yml
lib/fabsible/data/roles/exphost.instances/tasks/main.yml
lib/fabsible/data/roles/exphost.provision/tasks/.gitignore
lib/fabsible/data/roles/exphost.provision/tasks/.main.yml.swp
lib/fabsible/data/roles/exphost.provision/tasks/main.yml
lib/fabsible/data/roles/exphost.provision/tasks/users.yml
lib/fabsible/data/roles/exphost.universal_installer/tasks/app_loop.yml
lib/fabsible/data/roles/exphost.universal_installer/tasks/app_loop_priority.yml
lib/fabsible/data/roles/exphost.universal_installer/tasks/main.yml
lib/fabsible/data/roles/exphost.vars_merger/tasks/main.yml